[{"name":"sql.active_record","payload":{"sql":"SELECT  `patrons`.* FROM `patrons` WHERE `patrons`.`type` IN ('User') AND `patrons`.`confirmation_token` = 'CjzruHd-YZs6yi-Sixam' ORDER BY `patrons`.`id` ASC LIMIT 1","name":"User Load","connection_id":70317227863180,"statement_name":null,"binds":[]},"time":"2017-03-08T12:01:07.041+09:00","transaction_id":"5b85a188febdbf251f25","end":"2017-03-08T12:01:07.043+09:00","children":[],"duration":2.1919999999999997},{"name":"sql.active_record","payload":{"sql":"BEGIN","name":null,"connection_id":70317227863180,"statement_name":null,"binds":[]},"time":"2017-03-08T12:01:07.044+09:00","transaction_id":"5b85a188febdbf251f25","end":"2017-03-08T12:01:07.045+09:00","children":[],"duration":0.41300000000000003},{"name":"sql.active_record","payload":{"sql":"UPDATE `patrons` SET `confirmed_at` = '2017-03-08 03:01:07', `updated_at` = '2017-03-08 03:01:07' WHERE `patrons`.`id` = 2","name":"SQL","connection_id":70317227863180,"statement_name":null,"binds":[]},"time":"2017-03-08T12:01:07.048+09:00","transaction_id":"5b85a188febdbf251f25","end":"2017-03-08T12:01:07.053+09:00","children":[],"duration":5.611},{"name":"sql.active_record","payload":{"sql":"COMMIT","name":null,"connection_id":70317227863180,"statement_name":null,"binds":[]},"time":"2017-03-08T12:01:07.055+09:00","transaction_id":"5b85a188febdbf251f25","end":"2017-03-08T12:01:07.056+09:00","children":[],"duration":0.7380000000000001},{"name":"process_action.action_controller","payload":{"controller":"Devise::ConfirmationsController","action":"show","params":{"confirmation_token":"CjzruHd-YZs6yi-Sixam","controller":"devise/confirmations","action":"show"},"headers":"Not JSON Encodable","format":"html","method":"GET","path":"/users/confirmation?confirmation_token=CjzruHd-YZs6yi-Sixam","status":302,"view_runtime":null,"db_runtime":7.571000000000001},"time":"2017-03-08T12:01:07.038+09:00","transaction_id":"5b85a188febdbf251f25","end":"2017-03-08T12:01:07.058+09:00","children":[],"duration":19.986}]